.gitignore
Makefile
pyproject.toml
monolearn/GainanovFKB.py
monolearn/GainanovSAT.py
monolearn/LearnModule.py
monolearn/LevelLearn.py
monolearn/LowerSetLearn.py
monolearn/RandomLearn.py
monolearn/SparseSet.py
monolearn/__init__.py
monolearn/utils.py
monolearn.egg-info/PKG-INFO
monolearn.egg-info/SOURCES.txt
monolearn.egg-info/dependency_links.txt
monolearn.egg-info/requires.txt
monolearn.egg-info/top_level.txt
tests/test_Learn.py